{
"type": "FeatureCollection",
"name": "heliports",
"crs": { "type": "name", "properties": { "name": "urn:ogc:def:crs:OGC:1.3:CRS84" } },
"features": [
{ "type": "Feature", "properties": { "Field1": "Sarp Heliport", "Field2": 39.752685, "Field3": 30.638409 }, "geometry": { "type": "Point", "coordinates": [ 30.638409, 39.752685 ] } },
{ "type": "Feature", "properties": { "Field1": "Şehir Hastanesi Heliport", "Field2": 39.746882, "Field3": 30.596933 }, "geometry": { "type": "Point", "coordinates": [ 30.596933, 39.746882 ] } }
]
}
